{
  "RuleNumber": "3",
  "Name": "De Bal",
  "Questions": [
    {
      "QuestionNumber": "3.1",
      "Phrase": "Hoeveel kleuren mag de wedstrijdbal hebben?",
      "Answers": [
        {
          "AnswerNumber": "a",
          "Phrase": "1",
          "Correct": false
        },
        {
          "AnswerNumber": "b",
          "Phrase": "2",
          "Correct": false
        },
        {
          "AnswerNumber": "c",
          "Phrase": "3",
          "Correct": false
        },
        {
          "AnswerNumber": "d",
          "Phrase": "zoveel men wil",
          "Correct": true
        }
      ]
    },
    {
      "QuestionNumber": "3.2",
      "Phrase": "Welke van de volgende ballen moet de scheidrechter kiezen voor een wedstrijd heren senioren?",
      "Answers": [
        {
          "AnswerNumber": "a",
          "Phrase": "omtrek 57 cm, gewicht 450 g",
          "Correct": false
        },
        {
          "AnswerNumber": "b",
          "Phrase": "omtrek 58 cm, gewicht 400 g",
          "Correct": false
        },
        {
          "AnswerNumber": "c",
          "Phrase": "omtrek 59 cm, gewicht 425 g",
          "Correct": true
        },
        {
          "AnswerNumber": "d",
          "Phrase": "omtrek 60 cm, gewicht 500 g",
          "Correct": false
        }
      ]
    },
    {
      "QuestionNumber": "3.3",
      "Phrase": "Welke van de volgende ballen moet de scheidrechter kiezen voor een wedstrijd dames senioren?",
      "Answers": [
        {
          "AnswerNumber": "a",
          "Phrase": "omtrek 53 cm, gewicht 350 g",
          "Correct": false
        },
        {
          "AnswerNumber": "b",
          "Phrase": "omtrek 54 cm, gewicht 300 g",
          "Correct": false
        },
        {
          "AnswerNumber": "c",
          "Phrase": "omtrek 55 cm, gewicht 425 g",
          "Correct": false
        },
        {
          "AnswerNumber": "d",
          "Phrase": "omtrek 56 cm, gewicht 375 g",
          "Correct": true
        }
      ]
    },
    {
      "QuestionNumber": "3.4",
      "Phrase": "De scheidsrechters hebben besloten om de reservebal in het spel te brengen. Wanneer moet de wedstrijdbal weer gebruikt worden?",
      "Answers": [
        {
          "AnswerNumber": "a",
          "Phrase": "Bij de volgende spelonderbreking",
          "Correct": false
        },
        {
          "AnswerNumber": "b",
          "Phrase": "Hij kan niet opnieuw gebruikt worden, tenzij het onmogelijk wordt om met de reservebal verder te spelen",
          "Correct": false
        },
        {
          "AnswerNumber": "c",
          "Phrase": "Wanneer de scheidsrechters het aangewezen vinden dat hij weer gebruikt wordt",
          "Correct": true
        },
        {
          "AnswerNumber": "d",
          "Phrase": "Wanneer een der teams dit vraagt",
          "Correct": false
        }
      ]
    }
  ]
}